vmware/vapi/__init__.py
vmware/vapi/core.py
vmware/vapi/exception.py
vmware/vapi/message.py
vmware/vapi/wsgi.py
vmware/vapi/bindings/__init__.py
vmware/vapi/bindings/common.py
vmware/vapi/bindings/converter.py
vmware/vapi/bindings/datetime_helper.py
vmware/vapi/bindings/enum.py
vmware/vapi/bindings/error.py
vmware/vapi/bindings/http_helper.py
vmware/vapi/bindings/message.py
vmware/vapi/bindings/skeleton.py
vmware/vapi/bindings/struct.py
vmware/vapi/bindings/stub.py
vmware/vapi/bindings/task_helper.py
vmware/vapi/bindings/type.py
vmware/vapi/bindings/uri_helper.py
vmware/vapi/common/__init__.py
vmware/vapi/common/context.py
vmware/vapi/data/__init__.py
vmware/vapi/data/definition.py
vmware/vapi/data/type.py
vmware/vapi/data/validator.py
vmware/vapi/data/value.py
vmware/vapi/data/serializers/__init__.py
vmware/vapi/data/serializers/cleanjson.py
vmware/vapi/data/serializers/introspection.py
vmware/vapi/data/serializers/jsonrpc.py
vmware/vapi/data/serializers/python.py
vmware/vapi/data/serializers/rest.py
vmware/vapi/debug/__init__.py
vmware/vapi/debug/livedump.py
vmware/vapi/l10n/__init__.py
vmware/vapi/l10n/bindings.py
vmware/vapi/l10n/bundle.py
vmware/vapi/l10n/constants.py
vmware/vapi/l10n/formatter.py
vmware/vapi/l10n/runtime.py
vmware/vapi/l10n/utils.py
vmware/vapi/lib/__init__.py
vmware/vapi/lib/addr_url_parser.py
vmware/vapi/lib/connect.py
vmware/vapi/lib/constants.py
vmware/vapi/lib/context.py
vmware/vapi/lib/converter.py
vmware/vapi/lib/fingerprint.py
vmware/vapi/lib/jsonlib.py
vmware/vapi/lib/load.py
vmware/vapi/lib/log.py
vmware/vapi/lib/profiler.py
vmware/vapi/lib/rest.py
vmware/vapi/lib/ssl.py
vmware/vapi/lib/std.py
vmware/vapi/lib/thread_pool.py
vmware/vapi/lib/visitor.py
vmware/vapi/lib/workers_pool.py
vmware/vapi/protocol/__init__.py
vmware/vapi/protocol/client/__init__.py
vmware/vapi/protocol/client/connector.py
vmware/vapi/protocol/client/http_lib.py
vmware/vapi/protocol/client/local_connector.py
vmware/vapi/protocol/client/msg/__init__.py
vmware_vapi_runtime-2.52.0.dist-info/LICENSE
vmware_vapi_runtime-2.52.0.dist-info/METADATA
vmware_vapi_runtime-2.52.0.dist-info/WHEEL
vmware_vapi_runtime-2.52.0.dist-info/entry_points.txt
vmware_vapi_runtime-2.52.0.dist-info/top_level.txt
vmware_vapi_runtime-2.52.0.dist-info/RECORD
