Metadata-Version: 2.1
Name: vmware-vapi-runtime
Version: 2.52.0
Summary: VMware vAPI Runtime
Home-page: https://github.com/vmware/vsphere-automation-sdk-python
Author: Broadcom
License: License :: OSI Approved :: MIT License
Keywords: Broadcom,VCF,vSphere
Platform: UNKNOWN
Classifier: Development Status :: 5 - Production/Stable
Classifier: License :: OSI Approved :: MIT License
Classifier: Intended Audience :: Information Technology
Classifier: Intended Audience :: System Administrators
Classifier: Intended Audience :: Developers
Classifier: Environment :: No Input/Output (Daemon)
Classifier: Programming Language :: Python :: 3.8
Classifier: Programming Language :: Python :: 3.9
Classifier: Programming Language :: Python :: 3.10
Classifier: Programming Language :: Python :: 3.11
Classifier: Topic :: Software Development :: Libraries :: Python Modules
Classifier: Topic :: System :: Distributed Computing
Classifier: Operating System :: Microsoft :: Windows
Classifier: Operating System :: POSIX
Classifier: Operating System :: Unix
Classifier: Operating System :: MacOS
Requires-Dist: pyOpenSSL
Requires-Dist: requests (<3.0.0,>=2.0.0)
Requires-Dist: six (<2.0.0,>=1.0.0)
Provides-Extra: server
Requires-Dist: lxml (>=4.3.0) ; extra == 'server'
Requires-Dist: urllib3 (>=1.25.1) ; extra == 'server'
Requires-Dist: werkzeug (>=0.14.1) ; extra == 'server'
Provides-Extra: twisted
Requires-Dist: lxml (>=4.3.0) ; extra == 'twisted'
Requires-Dist: service-identity (>=18.0.0) ; extra == 'twisted'
Requires-Dist: twisted (>=18.0.0) ; extra == 'twisted'
Requires-Dist: urllib3 (>=1.25.1) ; extra == 'twisted'
Requires-Dist: werkzeug (>=0.14.1) ; extra == 'twisted'
